pennylane_calculquebec/__init__.py
pennylane_calculquebec/_version.py
pennylane_calculquebec/base_device.py
pennylane_calculquebec/device_exception.py
pennylane_calculquebec/exceptions.py
pennylane_calculquebec/logger.py
pennylane_calculquebec/monarq_backup.py
pennylane_calculquebec/monarq_data.py
pennylane_calculquebec/monarq_device.py
pennylane_calculquebec/monarq_sim.py
pennylane_calculquebec/pydoc_generator.py
pennylane_calculquebec/API/__init__.py
pennylane_calculquebec/API/adapter.py
pennylane_calculquebec/API/client.py
pennylane_calculquebec/API/job.py
pennylane_calculquebec/API/retry_decorator.py
pennylane_calculquebec/processing/__init__.py
pennylane_calculquebec/processing/custom_gates.py
pennylane_calculquebec/processing/monarq_postproc.py
pennylane_calculquebec/processing/monarq_preproc.py
pennylane_calculquebec/processing/config/__init__.py
pennylane_calculquebec/processing/config/processing_config.py
pennylane_calculquebec/processing/decompositions/native_decomp_functions.py
pennylane_calculquebec/processing/interfaces/__init__.py
pennylane_calculquebec/processing/interfaces/base_step.py
pennylane_calculquebec/processing/interfaces/post_proc_step.py
pennylane_calculquebec/processing/interfaces/pre_proc_step.py
pennylane_calculquebec/processing/optimization_methods/iterative_commute_and_merge.py
pennylane_calculquebec/processing/steps/__init__.py
pennylane_calculquebec/processing/steps/base_decomposition.py
pennylane_calculquebec/processing/steps/decompose_readout.py
pennylane_calculquebec/processing/steps/gate_noise_simulation.py
pennylane_calculquebec/processing/steps/native_decomposition.py
pennylane_calculquebec/processing/steps/optimization.py
pennylane_calculquebec/processing/steps/placement.py
pennylane_calculquebec/processing/steps/print_steps.py
pennylane_calculquebec/processing/steps/readout_error_mitigation.py
pennylane_calculquebec/processing/steps/readout_noise_simulation.py
pennylane_calculquebec/processing/steps/routing.py
pennylane_calculquebec-0.8.1.dist-info/licenses/LICENSE
pennylane_calculquebec-0.8.1.dist-info/METADATA
pennylane_calculquebec-0.8.1.dist-info/WHEEL
pennylane_calculquebec-0.8.1.dist-info/entry_points.txt
pennylane_calculquebec-0.8.1.dist-info/top_level.txt
pennylane_calculquebec-0.8.1.dist-info/RECORD
