Metadata-Version: 2.4
Name: pennylane-calculquebec
Version: 0.8.1
Summary: Pennylane plugin enabling seamless job execution on MonarQ, Calcul Québec’s nonprofit-hosted quantum computer
Maintainer-email: Calcul Québec <support@tech.alliancecan.ca>
License: Creative Commons
Project-URL: Source, https://github.com/calculquebec/pennylane-calculquebec
Classifier: Development Status :: 4 - Beta
Classifier: Environment :: Console
Classifier: Intended Audience :: Science/Research
Classifier: License :: OSI Approved :: Common Public License
Classifier: Natural Language :: English
Classifier: Operating System :: POSIX
Classifier: Operating System :: MacOS :: MacOS X
Classifier: Operating System :: POSIX :: Linux
Classifier: Operating System :: Microsoft :: Windows
Classifier: Programming Language :: Python
Classifier: Programming Language :: Python :: 3
Classifier: Programming Language :: Python :: 3.11
Classifier: Programming Language :: Python :: 3.12
Classifier: Programming Language :: Python :: 3 :: Only
Classifier: Topic :: Scientific/Engineering :: Physics
Requires-Python: >=3.11
License-File: LICENSE
Requires-Dist: numpy
Requires-Dist: pennylane~=0.43
Requires-Dist: networkx>=3.3
Provides-Extra: test
Requires-Dist: matplotlib; extra == "test"
Requires-Dist: pytest; extra == "test"
Requires-Dist: pytest-mock; extra == "test"
Requires-Dist: flaky; extra == "test"
Requires-Dist: tox; extra == "test"
Dynamic: license-file
